rabird.winio-0.2.2-nspkg.pth
rabird/winio.py
rabird.winio-0.2.2.dist-info/top_level.txt
rabird.winio-0.2.2.dist-info/namespace_packages.txt
rabird.winio-0.2.2.dist-info/pbr.json
rabird.winio-0.2.2.dist-info/METADATA
rabird.winio-0.2.2.dist-info/DESCRIPTION.rst
rabird.winio-0.2.2.dist-info/metadata.json
rabird.winio-0.2.2.dist-info/WHEEL
rabird.winio-0.2.2.dist-info/RECORD
