Metadata-Version: 2.0
Name: rabird.winio
Version: 0.2.2
Summary: A wrapper library for WinIO
Home-page: https://github.com/starofrainnight/rabird.winio
Author: Hong-She Liang
Author-email: starofrainnight@gmail.com
License: UNKNOWN
Platform: UNKNOWN
Classifier: Development Status :: 3 - Alpha
Classifier: Intended Audience :: Developers
Classifier: License :: OSI Approved :: MIT License
Classifier: Operating System :: Microsoft :: Windows
Classifier: Programming Language :: Python :: 2
Classifier: Programming Language :: Python :: 3
Classifier: Programming Language :: Python :: Implementation :: CPython
Classifier: Topic :: Software Development :: Libraries
Requires-Dist: rabird.core
Requires-Dist: winiobinary
